javascripthon-0.13-py3.10-nspkg.pth
metapensiero/pj/__init__.py
metapensiero/pj/__main__.py
metapensiero/pj/api.py
metapensiero/pj/compat.py
metapensiero/pj/snippets.py
metapensiero/pj/testing.py
metapensiero/pj/data/babel-6.18.1.min.js
metapensiero/pj/data/polyfill.min.js
metapensiero/pj/js_ast/__init__.py
metapensiero/pj/js_ast/base.py
metapensiero/pj/js_ast/blocks.py
metapensiero/pj/js_ast/bodies.py
metapensiero/pj/js_ast/classes.py
metapensiero/pj/js_ast/expressions.py
metapensiero/pj/js_ast/functions.py
metapensiero/pj/js_ast/literals.py
metapensiero/pj/js_ast/noops.py
metapensiero/pj/js_ast/operators.py
metapensiero/pj/js_ast/statements.py
metapensiero/pj/js_ast/util.py
metapensiero/pj/processor/__init__.py
metapensiero/pj/processor/exceptions.py
metapensiero/pj/processor/sourcemaps.py
metapensiero/pj/processor/transforming.py
metapensiero/pj/processor/util.py
metapensiero/pj/transformations/__init__.py
metapensiero/pj/transformations/classes.py
metapensiero/pj/transformations/common.py
metapensiero/pj/transformations/comprehensions.py
metapensiero/pj/transformations/exceptions.py
metapensiero/pj/transformations/forloops.py
metapensiero/pj/transformations/functions.py
metapensiero/pj/transformations/obvious.py
metapensiero/pj/transformations/special.py
javascripthon-0.13.dist-info/LICENSE.txt
javascripthon-0.13.dist-info/METADATA
javascripthon-0.13.dist-info/WHEEL
javascripthon-0.13.dist-info/entry_points.txt
javascripthon-0.13.dist-info/namespace_packages.txt
javascripthon-0.13.dist-info/top_level.txt
javascripthon-0.13.dist-info/RECORD
