Metadata-Version: 2.1
Name: javascripthon
Version: 0.13
Summary: Javascript for refined palates: a Python 3 to ES6 Javascript translator
Home-page: https://github.com/azazel75/metapensiero.pj
Author: Alberto Berti
Author-email: alberto@arstecnica.it
License: GPLv3+
Keywords: JavaScript EcmaScript compilation translation transpiling babel
Classifier: Development Status :: 5 - Production/Stable
Classifier: Programming Language :: Python :: 3
Classifier: Programming Language :: Python :: 3.7
Classifier: Programming Language :: Python :: 3.8
Classifier: Programming Language :: Python :: 3.9
Classifier: Programming Language :: Python :: 3.10
Classifier: Intended Audience :: Developers
Classifier: License :: OSI Approved :: GNU General Public License (GPL)
License-File: LICENSE.txt
Requires-Dist: setuptools
Requires-Dist: dukpy<=0.2.3
Provides-Extra: dev
Requires-Dist: metapensiero.tool.bump_version; extra == "dev"
Requires-Dist: readme_renderer; extra == "dev"
Provides-Extra: test
Requires-Dist: pytest; extra == "test"
Requires-Dist: pytest-cov; extra == "test"
Requires-Dist: meta; extra == "test"
